MANIFEST.in
README.rst
setup.py
docs/HISTORY.txt
docs/INSTALL.txt
docs/LICENSE.GPL
docs/LICENSE.txt
redturtle/__init__.py
redturtle.imagedevent.egg-info/PKG-INFO
redturtle.imagedevent.egg-info/SOURCES.txt
redturtle.imagedevent.egg-info/dependency_links.txt
redturtle.imagedevent.egg-info/entry_points.txt
redturtle.imagedevent.egg-info/namespace_packages.txt
redturtle.imagedevent.egg-info/not-zip-safe
redturtle.imagedevent.egg-info/requires.txt
redturtle.imagedevent.egg-info/top_level.txt
redturtle/imagedevent/README.txt
redturtle/imagedevent/__init__.py
redturtle/imagedevent/config.py
redturtle/imagedevent/configure.zcml
redturtle/imagedevent/extender.py
redturtle/imagedevent/interfaces.py
redturtle/imagedevent/migrator.py
redturtle/imagedevent/profiles.zcml
redturtle/imagedevent/setuphandlers.py
redturtle/imagedevent/vocabularies.py
redturtle/imagedevent/Extensions/__init__.py
redturtle/imagedevent/Extensions/install.py
redturtle/imagedevent/browser/__init__.py
redturtle/imagedevent/browser/configure.zcml
redturtle/imagedevent/browser/imagedevent.css
redturtle/imagedevent/browser/imagedevent_view.pt
redturtle/imagedevent/browser/migrateblobs.py
redturtle/imagedevent/content/__init__.py
redturtle/imagedevent/content/configure.zcml
redturtle/imagedevent/content/event.py
redturtle/imagedevent/i18n/plone-it.po
redturtle/imagedevent/locales/i18n.sh
redturtle/imagedevent/locales/redturtle.imagedevent-manual.pot
redturtle/imagedevent/locales/redturtle.imagedevent.pot
redturtle/imagedevent/locales/it/LC_MESSAGES/redturtle.imagedevent.mo
redturtle/imagedevent/locales/it/LC_MESSAGES/redturtle.imagedevent.po
redturtle/imagedevent/profiles/default/catalog.xml
redturtle/imagedevent/profiles/default/cssregistry.xml
redturtle/imagedevent/profiles/default/import_steps.xml
redturtle/imagedevent/profiles/default/metadata.xml
redturtle/imagedevent/profiles/default/portal_atct.xml
redturtle/imagedevent/profiles/default/redturtle.imagedevent_various.txt
redturtle/imagedevent/profiles/default/types.xml
redturtle/imagedevent/profiles/default/types/Event.xml
redturtle/imagedevent/profiles/new-collections-support/registry.xml
redturtle/imagedevent/profiles/uninstall/cssregistry.xml
redturtle/imagedevent/tests/__init__.py
redturtle/imagedevent/tests/base.py
redturtle/imagedevent/tests/test_doctest.py