Metadata-Version: 1.1
Name: redturtle.imagedevent
Version: 1.0.2
Summary: A replacement of the Event content type for Plone, with image field and separate keyword and event type fields.
Home-page: http://plone.org/products/redturtle.imagedevent
Author: RedTurtle Technology
Author-email: sviluppoplone@redturtle.it
License: GPL
Keywords: plone event image content plonegov
Platform: UNKNOWN
Classifier: Framework :: Plone
Classifier: Framework :: Plone :: 4.0
Classifier: Framework :: Plone :: 4.1
Classifier: Framework :: Plone :: 4.2
Classifier: Framework :: Plone :: 4.3
Classifier: Development Status :: 5 - Production/Stable
Classifier: Topic :: Software Development :: Libraries :: Python Modules
Classifier: License :: OSI Approved :: GNU General Public License (GPL)
